video_text_summarizer/__init__.py
video_text_summarizer/main.py
video_text_summarizer/prompts.py
video_text_summarizer-2025.12.21114602.dist-info/METADATA
video_text_summarizer-2025.12.21114602.dist-info/WHEEL
video_text_summarizer-2025.12.21114602.dist-info/top_level.txt
video_text_summarizer-2025.12.21114602.dist-info/RECORD
