Metadata-Version: 2.4
Name: video-text-summarizer
Version: 2025.12.21114602
Summary: A new package designed to analyze and summarize video content by processing pre-extracted textual information such as transcripts, subtitles, and descriptions. It leverages structured pattern matching
Author-email: video-text-summarizer <hi@eugene.plus>
License: MIT
Project-URL: Homepage, https://github.com/chigwell/video-text-summarizer
Requires-Python: >=3.9
Requires-Dist: langchain-llm7>=0.0.0
Requires-Dist: llmatch-messages>=0.0.0
Requires-Dist: langchain-core>=0.3.0
